pyclesperanto/__init__.py
pyclesperanto/_array.py
pyclesperanto/_bia_bob_plugins.py
pyclesperanto/_categories.py
pyclesperanto/_core.py
pyclesperanto/_decorators.py
pyclesperanto/_functionalities.py
pyclesperanto/_interroperability.py
pyclesperanto/_memory.py
pyclesperanto/_operators.py
pyclesperanto/_pyclesperanto.cpython-39-x86_64-linux-gnu.so
pyclesperanto/_tier1.py
pyclesperanto/_tier2.py
pyclesperanto/_tier3.py
pyclesperanto/_tier4.py
pyclesperanto/_tier5.py
pyclesperanto/_tier6.py
pyclesperanto/_tier7.py
pyclesperanto/_tier8.py
pyclesperanto/_utils.py
pyclesperanto/_version.py
pyclesperanto/__experimental__/__init__.py
pyclesperanto/__experimental__/clahe.cl
pyclesperanto/__experimental__/clahe.py
pyclesperanto.libs/libOpenCL-b56acc03.so.1.0.0
pyclesperanto-0.19.0.dist-info/METADATA
pyclesperanto-0.19.0.dist-info/WHEEL
pyclesperanto-0.19.0.dist-info/entry_points.txt
pyclesperanto-0.19.0.dist-info/RECORD
pyclesperanto-0.19.0.dist-info/licenses/LICENSE
