Metadata-Version: 2.2
Name: pyclesperanto
Version: 0.19.0
Summary: GPU-accelerated image processing in python using OpenCL
Keywords: image processing,GPU,OpenCL,scientific computing
Author-Email: Stephane Rigaud <stephane.rigaud@pasteur.fr>, Robert Haase <robert.haase@uni-leipzig.de>
License: Copyright 2024 Stéphane Rigaud, Robert Haase, Institut Pasteur Paris, Max Planck Institute for Molecular Cell Biology and Genetics Dresden, ScaDS.AI, Leipzig University
Classifier: Development Status :: 3 - Alpha
Classifier: Programming Language :: C++
Classifier: Programming Language :: Python :: 3
Classifier: License :: OSI Approved :: BSD License
Classifier: Operating System :: OS Independent
Classifier: Intended Audience :: Science/Research
Classifier: Intended Audience :: Developers
Classifier: Topic :: Software Development :: Libraries :: Python Modules
Classifier: Topic :: Scientific/Engineering :: Image Processing
Classifier: Topic :: Scientific/Engineering :: Information Analysis
Project-URL: Documentation, https://clesperanto.github.io/pyclesperanto/
Project-URL: Examples, https://clesperanto.github.io/pyclesperanto/demos/
Project-URL: Issues, https://github.com/clEsperanto/pyclesperanto/issues
Project-URL: Source, https://github.com/clEsperanto/pyclesperanto/
Requires-Python: >=3.8
Requires-Dist: numpy
Requires-Dist: toolz
Requires-Dist: matplotlib
Requires-Dist: toml
